imagera/__init__.py
imagera/events/__init__.py
imagera/events/events.py
imagera/histogram/__init__.py
imagera/histogram/histogram_model.py
imagera/histogram/histogram_view.py
imagera/histogram/histogram_vm.py
imagera/image/__init__.py
imagera/image/image.py
imagera/image/image_aid.py
imagera/image/image_bundle.py
imagera/optics/surface_visualizer.py
imagera/pil/__init__.py
imagera/pil/pil_utils.py
imagera/plotter/__init__.py
imagera/plotter/aid.py
imagera/plotter/cmap.py
imagera/plotter/fit_title.py
imagera/plotter/helpers.py
imagera/plotter/plot_parameters.py
imagera/plotter/plt_scalar2d.py
imagera/plotter/plt_scalars2d.py
imagera/plotter/values_minmax.py
imagera/pv_vis/__init__.py
imagera/pv_vis/pv_scalar_field_2d.py
imagera/reader/__init__.py
imagera/reader/image_reader.py
imagera/viewer/Model/__init__.py
imagera/viewer/Model/display.py
imagera/viewer/Model/view_port.py
imagera/viewer/VM/__init__.py
imagera/viewer/VM/control.py
imagera/viewer/VM/display.py
imagera/viewer/VM/image_viewer.py
imagera/viewer/VM/info.py
imagera/viewer/VM/view_port.py
imagera/viewer/View/__init__.py
imagera/viewer/View/control.py
imagera/viewer/View/display.py
imagera/viewer/View/display_label.py
imagera/viewer/View/fit.py
imagera/viewer/View/image_viewer.py
imagera/viewer/View/info.py
imagera/viewer/View/view_port.py
imagera/viewer/View/zoom.py
imagera-0.4.1.dist-info/licenses/LICENSE
imagera-0.4.1.dist-info/METADATA
imagera-0.4.1.dist-info/WHEEL
imagera-0.4.1.dist-info/top_level.txt
imagera-0.4.1.dist-info/RECORD
