Metadata-Version: 2.4
Name: imagera
Version: 0.4.1
Summary: Image, plot, visiual representaion
Author-email: Anton Sharapov <sharapov.anton@gmail.com>
License-Expression: MIT
Project-URL: Homepage, https://github.com/SharapovAnton/Imagera
Project-URL: Source, https://github.com/SharapovAnton/Imagera
Project-URL: Issues, https://github.com/SharapovAnton/Imagera/issues
Classifier: Programming Language :: Python :: 3
Classifier: Programming Language :: Python :: 3 :: Only
Classifier: Operating System :: OS Independent
Classifier: Topic :: Software Development :: Libraries
Classifier: Typing :: Typed
Requires-Python: >=3.8
License-File: LICENSE
Requires-Dist: numpy>=1.23
Requires-Dist: opencv-python>=4.12.0.88
Requires-Dist: allytools>=0.6.0
Requires-Dist: matplotlib>=3.10.7
Requires-Dist: pyvista>=0.46.4
Provides-Extra: dev
Requires-Dist: pytest; extra == "dev"
Requires-Dist: mypy; extra == "dev"
Requires-Dist: ruff; extra == "dev"
Provides-Extra: qa
Requires-Dist: tox; extra == "qa"
Requires-Dist: pre-commit; extra == "qa"
Provides-Extra: gui
Requires-Dist: PyQt5; extra == "gui"
Dynamic: license-file
